rqtest
