Metadata-Version: 1.0
Name: rqtest
Version: 0.0.5
Summary: test tool based on requests
Home-page: https://github.com/qorzj/rqtest
Author: qorzj
Author-email: UNKNOWN
License: MIT
Keywords: rqtest requests
Platform: any
